cloudshell/__init__.py
cloudshell/networking/__init__.py
cloudshell/networking/cisco/__init__.py
cloudshell/networking/cisco/nxos/__init__.py
cloudshell/networking/cisco/nxos/cli/__init__.py
cloudshell/networking/cisco/nxos/cli/cisco_nxos_cli_handler.py
cloudshell/networking/cisco/nxos/command_actions/__init__.py
cloudshell/networking/cisco/nxos/command_actions/nxos_add_remove_vlan_actions.py
cloudshell/networking/cisco/nxos/command_actions/nxos_iface_actions.py
cloudshell/networking/cisco/nxos/command_templates/__init__.py
cloudshell/networking/cisco/nxos/command_templates/nxos_add_remove_vlan.py
cloudshell/networking/cisco/nxos/flows/__init__.py
cloudshell/networking/cisco/nxos/flows/cisco_nxos_configuration_flow.py
cloudshell/networking/cisco/nxos/flows/cisco_nxos_connectivity_flow.py
cloudshell_networking_cisco_nxos-6.0.0.dist-info/METADATA
cloudshell_networking_cisco_nxos-6.0.0.dist-info/WHEEL
cloudshell_networking_cisco_nxos-6.0.0.dist-info/top_level.txt
cloudshell_networking_cisco_nxos-6.0.0.dist-info/RECORD
