Metadata-Version: 2.1
Name: cloudshell-networking-cisco-nxos
Version: 6.0.0
Summary: QualiSystems networking cisco NxOS specific Package
Home-page: http://www.qualisystems.com/
Author: QualiSystems
Author-email: info@qualisystems.com
License: UNKNOWN
Platform: UNKNOWN
Requires-Python: ~=3.7
Requires-Dist: setuptools (>=40.0)
Requires-Dist: cloudshell-networking-cisco (~=6.0)
